deply/__init__.py
deply/code_analyzer.py
deply/config_parser.py
deply/deply_runner.py
deply/main.py
deply/collectors/__init__.py
deply/collectors/base_collector.py
deply/collectors/bool_collector.py
deply/collectors/class_inherits_collector.py
deply/collectors/class_name_regex_collector.py
deply/collectors/collector_factory.py
deply/collectors/decorator_usage_collector.py
deply/collectors/directory_collector.py
deply/collectors/file_regex_collector.py
deply/collectors/function_name_regex_collector.py
deply/diagrams/__init__.py
deply/diagrams/marmaid_diagram_builder.py
deply/models/__init__.py
deply/models/code_element.py
deply/models/dependency.py
deply/models/layer.py
deply/models/violation.py
deply/models/violation_types.py
deply/reports/__init__.py
deply/reports/report_generator.py
deply/reports/formats/__init__.py
deply/reports/formats/github_actions_report.py
deply/reports/formats/json_report.py
deply/reports/formats/text_report.py
deply/rules/__init__.py
deply/rules/base_rule.py
deply/rules/bool_rule.py
deply/rules/class_decorator_rule.py
deply/rules/class_naming_rule.py
deply/rules/dependency_rule.py
deply/rules/function_decorator_rule.py
deply/rules/function_naming_rule.py
deply/rules/inheritance_rule.py
deply/rules/rule_factory.py
deply/utils/__init__.py
deply/utils/ast_utils.py
deply/utils/dependency_visitor.py
deply/utils/ignore_parser.py
deply-0.8.0.dist-info/licenses/LICENSE
tests/__init__.py
tests/test.py
tests/test_ast_utils.py
tests/test_class_decorator_usage_rule.py
tests/test_class_method_call_violation.py
tests/test_collector_factory.py
tests/test_collectors.py
tests/test_deply_runner.py
tests/test_false_dependency_path.py
tests/test_ignore_parser.py
tests/test_mermaid_diagram_builder.py
tests/test_rules.py
deply-0.8.0.dist-info/METADATA
deply-0.8.0.dist-info/WHEEL
deply-0.8.0.dist-info/entry_points.txt
deply-0.8.0.dist-info/top_level.txt
deply-0.8.0.dist-info/RECORD
