Metadata-Version: 2.4
Name: deply
Version: 0.8.0
Summary: A tool to enforce architectural patterns in python projects
Home-page: https://github.com/vashkatsi/deply
Author: Archil Abuladze
Author-email: armiworker@gmail.com
Project-URL: Bug Tracker, https://github.com/vashkatsi/deply/issues
Classifier: Programming Language :: Python :: 3
Classifier: Operating System :: OS Independent
Requires-Python: >=3.6
License-File: LICENSE
Requires-Dist: PyYAML>=5.1
Dynamic: author
Dynamic: author-email
Dynamic: classifier
Dynamic: description
Dynamic: description-content-type
Dynamic: home-page
Dynamic: license-file
Dynamic: project-url
Dynamic: requires-dist
Dynamic: requires-python
Dynamic: summary
